{
  "id": "edgecommons-streamlog-node-2026-07-18",
  "display_name": "@edgecommons/streamlog-node",
  "campaign": null,
  "detection_source": "osv",
  "packages": [
    {
      "package": "@edgecommons/streamlog-node",
      "ecosystem": "npm",
      "versions": [
        "0.0.1-0"
      ],
      "osv_entries": [
        {
          "osv_id": "MAL-2026-10763",
          "osv_published_at": "2026-07-16T00:00:00Z"
        }
      ]
    }
  ],
  "malware_type": "malware",
  "attestd_detected_at": "2026-07-18T02:03:08Z",
  "flagged_at": null,
  "confirmed_at": "2026-07-18T02:03:08Z",
  "osv_earliest_published_at": "2026-07-16T00:00:00Z",
  "hours_ahead_of_osv": null,
  "hours_ahead_of_press": null,
  "press_coverage_at": null,
  "press_urls": [],
  "advisory_url": "",
  "ledger_commit_at": "2026-07-18T02:03:18Z"
}
